django_prices_openexchangerates/__init__.py
django_prices_openexchangerates/admin.py
django_prices_openexchangerates/apps.py
django_prices_openexchangerates/currencies.py
django_prices_openexchangerates/models.py
django_prices_openexchangerates/tasks.py
django_prices_openexchangerates/management/__init__.py
django_prices_openexchangerates/management/commands/__init__.py
django_prices_openexchangerates/management/commands/update_exchange_rates.py
django_prices_openexchangerates/migrations/0001_initial.py
django_prices_openexchangerates/migrations/0002_auto_20160329_0702.py
django_prices_openexchangerates/migrations/0003_auto_20161018_0707.py
django_prices_openexchangerates/migrations/0004_auto_20170316_0944.py
django_prices_openexchangerates/migrations/0005_auto_20190124_1008.py
django_prices_openexchangerates/migrations/__init__.py
django_prices_openexchangerates/templatetags/__init__.py
django_prices_openexchangerates/templatetags/prices_multicurrency.py
django_prices_openexchangerates-1.2.0.dist-info/LICENSE
django_prices_openexchangerates-1.2.0.dist-info/METADATA
django_prices_openexchangerates-1.2.0.dist-info/WHEEL
django_prices_openexchangerates-1.2.0.dist-info/top_level.txt
django_prices_openexchangerates-1.2.0.dist-info/RECORD
